{
  "updated_at": "2026-04-02T13:50:52.244466+00:00",
  "balance": {
    "available": 1501.78,
    "portfolio_value": 1681.78,
    "deployed": 180.0
  },
  "btc": {
    "price": 66031.16,
    "ema200": 67721.05281270086,
    "ema200_distance_pct": -2.7,
    "rsi": 28.353049170400965,
    "eagle": "CAPITULATION",
    "eagle_confidence": 41.0,
    "eagle_cvd": "STRONG BEARISH",
    "nano": "CAPITULATION",
    "nano_position_pct": 50.5,
    "nano_zone_weight": "NEUTRAL",
    "nano_oi_context": "GRINDING \u2014 Flat OI + Capitulation = Slow bleed, floor weakening",
    "nano_direction_bias": "NEUTRAL",
    "vulture_bias": "LONG",
    "vulture_stack": "\ud83d\udcc9 BEARISH STACK (price < EMA9 < EMA21)",
    "trend": "\ud83d\udfe2 ACCUMULATION ZONE \u2014 Bullish at floor (LONG SIGNAL)",
    "rr_best_long": 69.9,
    "rr_best_short": 0.0,
    "rr_best_timeframe": "4h",
    "rr_long_1h": 56.8,
    "rr_short_1h": 0.0,
    "rr_long_6h": 3.6,
    "rr_short_6h": 0.3,
    "levels": {
      "f5m": 65696.96,
      "f1h": 65696.96,
      "f4h": 65696.96,
      "c1h": 68652.0,
      "c4h": 69285.99,
      "c6h": 69285.99
    }
  },
  "eth": {
    "price": 2027.46,
    "ema200": 2068.200266367307,
    "ema200_distance_pct": -2.37,
    "rsi": 24.873998993991037,
    "eagle": "CAPITULATION",
    "eagle_confidence": 28.0,
    "eagle_cvd": "MILD BULLISH",
    "nano": "ACCUMULATION",
    "nano_position_pct": 53.7,
    "nano_zone_weight": "NEUTRAL",
    "nano_oi_context": "STALEMATE \u2014 Flat OI + Accumulation = Waiting for catalyst",
    "nano_direction_bias": "NEUTRAL",
    "vulture_bias": "LONG",
    "vulture_stack": "\ud83d\udcc9 BEARISH STACK (price < EMA9 < EMA21)",
    "trend": "\ud83d\udfe2 ACCUMULATION ZONE \u2014 Bullish at floor (LONG SIGNAL)",
    "rr_best_long": 47.7,
    "rr_best_short": 0.0,
    "rr_best_timeframe": "1h",
    "rr_long_1h": 47.7,
    "rr_short_1h": 0.0,
    "rr_long_6h": 1.8,
    "rr_short_6h": 0.5,
    "levels": {
      "f5m": 2015.85,
      "f1h": 2015.85,
      "f4h": 2010.09,
      "c1h": 2165.0,
      "c4h": 2167.56,
      "c6h": 2167.56
    }
  },
  "symphony": {
    "state": "RANGE_BOUND",
    "confidence": 30
  },
  "macro": {
    "fg": 12,
    "weatherman": 1,
    "bias": "LEAN LONG"
  },
  "positions": [
    {
      "ticker": "KXBTCD-26APR0317-T71299.99",
      "asset": "BTC",
      "strike": 71300,
      "side": "yes",
      "qty": 2000,
      "entry": 0.8793,
      "market_value": 180.0,
      "cost_basis": 1758.6
    }
  ],
  "sell_orders": [],
  "buy_traps": [
    {
      "ticker": "KXBTCD-26APR0317-T71299.99",
      "asset": "BTC",
      "strike": 71300,
      "side": "yes",
      "price": 0.01,
      "qty": 2000,
      "remaining": 2000,
      "action": "buy"
    }
  ],
  "catalysts": [
    {
      "label": "JOLTS",
      "date": "2026-03-31T14:00:00Z",
      "risk": "HIGH"
    },
    {
      "label": "ADP",
      "date": "2026-04-01T12:15:00Z",
      "risk": "MED"
    },
    {
      "label": "ISM Mfg",
      "date": "2026-04-01T14:00:00Z",
      "risk": "MED"
    },
    {
      "label": "Tariff Day",
      "date": "2026-04-02T16:00:00Z",
      "risk": "MAX"
    },
    {
      "label": "NFP + Settle",
      "date": "2026-04-03T12:30:00Z",
      "risk": "MAX"
    }
  ],
  "price_history": {
    "BTC": {
      "series": [
        {
          "ts": "2026-04-02T01:46:56Z",
          "price": 67235.72,
          "eagle_phase": "NEUTRAL"
        },
        {
          "ts": "2026-04-02T02:17:09Z",
          "price": 66903.99,
          "eagle_phase": "CAPITULATION"
        },
        {
          "ts": "2026-04-02T02:47:25Z",
          "price": 66830.41,
          "eagle_phase": "CAPITULATION"
        },
        {
          "ts": "2026-04-02T03:17:34Z",
          "price": 66806.98,
          "eagle_phase": "CAPITULATION"
        },
        {
          "ts": "2026-04-02T03:48:10Z",
          "price": 66555.66,
          "eagle_phase": "CAPITULATION"
        },
        {
          "ts": "2026-04-02T04:18:05Z",
          "price": 66550.23,
          "eagle_phase": "CAPITULATION"
        },
        {
          "ts": "2026-04-02T04:49:02Z",
          "price": 66345.77,
          "eagle_phase": "CAPITULATION"
        },
        {
          "ts": "2026-04-02T05:19:19Z",
          "price": 66384.33,
          "eagle_phase": "NEUTRAL"
        },
        {
          "ts": "2026-04-02T05:49:35Z",
          "price": 66471.37,
          "eagle_phase": "ACCUMULATION"
        },
        {
          "ts": "2026-04-02T06:19:51Z",
          "price": 66785.04,
          "eagle_phase": "ACCUMULATION"
        },
        {
          "ts": "2026-04-02T06:50:05Z",
          "price": 66597.23,
          "eagle_phase": "ACCUMULATION"
        },
        {
          "ts": "2026-04-02T07:20:28Z",
          "price": 66673.67,
          "eagle_phase": "NEUTRAL"
        },
        {
          "ts": "2026-04-02T07:50:38Z",
          "price": 66887.48,
          "eagle_phase": "ACCUMULATION"
        },
        {
          "ts": "2026-04-02T08:20:52Z",
          "price": 66679.96,
          "eagle_phase": "ACCUMULATION"
        },
        {
          "ts": "2026-04-02T08:51:00Z",
          "price": 66504.99,
          "eagle_phase": "NEUTRAL"
        },
        {
          "ts": "2026-04-02T09:21:33Z",
          "price": 66397.51,
          "eagle_phase": "CAPITULATION"
        },
        {
          "ts": "2026-04-02T09:51:46Z",
          "price": 66385.0,
          "eagle_phase": "CAPITULATION"
        },
        {
          "ts": "2026-04-02T10:22:01Z",
          "price": 66317.49,
          "eagle_phase": "CAPITULATION"
        },
        {
          "ts": "2026-04-02T10:52:43Z",
          "price": 66479.29,
          "eagle_phase": "NEUTRAL"
        },
        {
          "ts": "2026-04-02T11:22:54Z",
          "price": 66389.33,
          "eagle_phase": "NEUTRAL"
        },
        {
          "ts": "2026-04-02T11:53:09Z",
          "price": 66278.0,
          "eagle_phase": "ACCUMULATION"
        },
        {
          "ts": "2026-04-02T12:23:25Z",
          "price": 66026.98,
          "eagle_phase": "CAPITULATION"
        },
        {
          "ts": "2026-04-02T12:53:45Z",
          "price": 66083.98,
          "eagle_phase": "NEUTRAL"
        },
        {
          "ts": "2026-04-02T13:23:53Z",
          "price": 65946.11,
          "eagle_phase": "CAPITULATION"
        }
      ],
      "high": 67235.72,
      "low": 65946.11
    },
    "ETH": {
      "series": [
        {
          "ts": "2026-04-02T01:46:56Z",
          "price": 2097.58,
          "eagle_phase": "CAPITULATION"
        },
        {
          "ts": "2026-04-02T02:17:09Z",
          "price": 2080.46,
          "eagle_phase": "CAPITULATION"
        },
        {
          "ts": "2026-04-02T02:47:25Z",
          "price": 2070.38,
          "eagle_phase": "CAPITULATION"
        },
        {
          "ts": "2026-04-02T03:17:34Z",
          "price": 2070.96,
          "eagle_phase": "CAPITULATION"
        },
        {
          "ts": "2026-04-02T03:48:10Z",
          "price": 2054.5,
          "eagle_phase": "CAPITULATION"
        },
        {
          "ts": "2026-04-02T04:18:05Z",
          "price": 2055.1,
          "eagle_phase": "CAPITULATION"
        },
        {
          "ts": "2026-04-02T04:49:02Z",
          "price": 2044.06,
          "eagle_phase": "CAPITULATION"
        },
        {
          "ts": "2026-04-02T05:19:19Z",
          "price": 2044.74,
          "eagle_phase": "CAPITULATION"
        },
        {
          "ts": "2026-04-02T05:49:35Z",
          "price": 2047.39,
          "eagle_phase": "CAPITULATION"
        },
        {
          "ts": "2026-04-02T06:19:51Z",
          "price": 2052.37,
          "eagle_phase": "NEUTRAL"
        },
        {
          "ts": "2026-04-02T06:50:05Z",
          "price": 2047.23,
          "eagle_phase": "CAPITULATION"
        },
        {
          "ts": "2026-04-02T07:20:28Z",
          "price": 2048.1,
          "eagle_phase": "NEUTRAL"
        },
        {
          "ts": "2026-04-02T07:50:38Z",
          "price": 2055.4,
          "eagle_phase": "NEUTRAL"
        },
        {
          "ts": "2026-04-02T08:20:52Z",
          "price": 2049.94,
          "eagle_phase": "NEUTRAL"
        },
        {
          "ts": "2026-04-02T08:51:00Z",
          "price": 2046.71,
          "eagle_phase": "NEUTRAL"
        },
        {
          "ts": "2026-04-02T09:21:33Z",
          "price": 2043.59,
          "eagle_phase": "CAPITULATION"
        },
        {
          "ts": "2026-04-02T09:51:46Z",
          "price": 2043.8,
          "eagle_phase": "CAPITULATION"
        },
        {
          "ts": "2026-04-02T10:22:01Z",
          "price": 2033.82,
          "eagle_phase": "CAPITULATION"
        },
        {
          "ts": "2026-04-02T10:52:43Z",
          "price": 2038.35,
          "eagle_phase": "NEUTRAL"
        },
        {
          "ts": "2026-04-02T11:22:54Z",
          "price": 2034.99,
          "eagle_phase": "NEUTRAL"
        },
        {
          "ts": "2026-04-02T11:53:09Z",
          "price": 2032.89,
          "eagle_phase": "ACCUMULATION"
        },
        {
          "ts": "2026-04-02T12:23:25Z",
          "price": 2027.95,
          "eagle_phase": "CAPITULATION"
        },
        {
          "ts": "2026-04-02T12:53:45Z",
          "price": 2027.01,
          "eagle_phase": "NEUTRAL"
        },
        {
          "ts": "2026-04-02T13:23:53Z",
          "price": 2021.71,
          "eagle_phase": "CAPITULATION"
        }
      ],
      "high": 2097.58,
      "low": 2021.71
    }
  },
  "fleet_summary": {
    "BTC": {
      "price": 66031.16,
      "eagle": "CAPITULATION",
      "nano": "CAPITULATION",
      "cvd": "STRONG BEARISH",
      "rsi": 28.353049170400965,
      "ema200_dist": -2.7,
      "rr_long": 69.9,
      "trend": "\ud83d\udfe2 ACCUMULATION ZONE \u2014 Bullish at floor (LONG SIGNAL)",
      "funding": -0.0007
    },
    "ETH": {
      "price": 2027.46,
      "eagle": "CAPITULATION",
      "nano": "ACCUMULATION",
      "cvd": "MILD BULLISH",
      "rsi": 24.873998993991037,
      "ema200_dist": -2.37,
      "rr_long": 47.7,
      "trend": "\ud83d\udfe2 ACCUMULATION ZONE \u2014 Bullish at floor (LONG SIGNAL)",
      "funding": -0.0012000000000000001
    },
    "SOL": {
      "price": 77.32,
      "eagle": "CAPITULATION",
      "nano": "CAPITULATION",
      "cvd": "NEUTRAL",
      "rsi": 25.04653777839023,
      "ema200_dist": -7.91,
      "rr_long": 66.8,
      "trend": "\ud83d\udcc8 BULLISH \u2014 Confirmed uptrend (long-friendly, short-cautious)",
      "funding": -0.0012000000000000001
    },
    "XRP": {
      "price": 1.2829,
      "eagle": "CAPITULATION",
      "nano": "ACCUMULATION",
      "cvd": "NEUTRAL",
      "rsi": 20.99813915794104,
      "ema200_dist": -4.92,
      "rr_long": 1089.0,
      "trend": "\ud83d\udfe2 ACCUMULATION ZONE \u2014 Bullish at floor (LONG SIGNAL)",
      "funding": -0.0014
    },
    "DOGE": {
      "price": 0.08944,
      "eagle": "CAPITULATION",
      "nano": "ACCUMULATION",
      "cvd": "STRONG BULLISH",
      "rsi": 29.933083602976737,
      "ema200_dist": -2.71,
      "rr_long": 37.5,
      "trend": "\ud83d\udfe2 ACCUMULATION ZONE \u2014 Bullish at floor (LONG SIGNAL)",
      "funding": -0.0009
    },
    "BNB": {
      "price": 571.13,
      "eagle": "CAPITULATION",
      "nano": "CAPITULATION",
      "cvd": "STRONG BULLISH",
      "rsi": 15.601602732182045,
      "ema200_dist": -7.13,
      "rr_long": 0,
      "trend": "\ud83d\udfe2 ACCUMULATION ZONE \u2014 Bullish at floor (LONG SIGNAL)",
      "funding": 0.001
    },
    "HYPE": {
      "price": 34.57,
      "eagle": "NEUTRAL",
      "nano": null,
      "cvd": "STRONG BEARISH",
      "rsi": 24.69338550603949,
      "ema200_dist": -8.16,
      "rr_long": 928.0,
      "trend": "\ud83d\udfe2 ACCUMULATION ZONE \u2014 Bullish at floor (LONG SIGNAL)",
      "funding": null
    },
    "TAO": {
      "price": 298.38,
      "eagle": "CAPITULATION",
      "nano": null,
      "cvd": "STRONG BULLISH",
      "rsi": 36.7573892161012,
      "ema200_dist": -4.83,
      "rr_long": 9.6,
      "trend": "\ud83d\udcc8 BULLISH \u2014 Confirmed uptrend (long-friendly, short-cautious)",
      "funding": null
    },
    "ZEC": {
      "price": 233.66,
      "eagle": "ACCUMULATION",
      "nano": "ACCUMULATION",
      "cvd": "STRONG BULLISH",
      "rsi": 36.15923452242342,
      "ema200_dist": 0.25,
      "rr_long": 19.1,
      "trend": "\ud83d\udcc8 BULLISH \u2014 Confirmed uptrend (long-friendly, short-cautious)",
      "funding": -9.999999999999999e-05
    },
    "LINK": {
      "price": 8.462,
      "eagle": "NEUTRAL",
      "nano": "ACCUMULATION",
      "cvd": "STRONG BULLISH",
      "rsi": 21.111388176938092,
      "ema200_dist": -3.64,
      "rr_long": 44.1,
      "trend": "\ud83d\udfe2 ACCUMULATION ZONE \u2014 Bullish at floor (LONG SIGNAL)",
      "funding": -0.0013
    },
    "BCH": {
      "price": 442.68,
      "eagle": "CAPITULATION",
      "nano": "ACCUMULATION",
      "cvd": "STRONG BULLISH",
      "rsi": 30.17061988681992,
      "ema200_dist": -4.47,
      "rr_long": 14.3,
      "trend": "\ud83d\udcc8 BULLISH \u2014 Confirmed uptrend (long-friendly, short-cautious)",
      "funding": -0.00039999999999999996
    }
  },
  "top_edges": [],
  "ledger": {
    "total_trades": 22,
    "wins": 19,
    "losses": 3,
    "win_rate": 86.4,
    "realized_pnl": 1151.99,
    "week_pnl": 499.21
  }
}