{
  "updated_at": "2026-04-19T16:08:49.265648+00:00",
  "balance": {
    "available": 7.16,
    "portfolio_value": 99.06,
    "deployed": 91.9
  },
  "btc": {
    "price": 75816.0,
    "ema200": 74576.59209805088,
    "ema200_distance_pct": 1.65,
    "rsi": 51.20582050297455,
    "eagle": "NEUTRAL",
    "eagle_confidence": 30.0,
    "eagle_cvd": "STRONG BEARISH",
    "nano": "DISTRIBUTION",
    "nano_position_pct": 47.3,
    "nano_zone_weight": "NEUTRAL",
    "nano_oi_context": "BALANCED \u2014 Flat OI + Distribution = No strong conviction",
    "nano_direction_bias": "NEUTRAL",
    "vulture_bias": "SHORT",
    "vulture_stack": "\u2696\ufe0f FLAT \u2014 EMAs converging",
    "trend": "\ud83d\udcc8 BULLISH \u2014 Confirmed uptrend (long-friendly, short-cautious)",
    "rr_best_long": 1.0,
    "rr_best_short": 1.0,
    "rr_best_timeframe": "4h",
    "rr_long_1h": 0.5,
    "rr_short_1h": 1.9,
    "rr_long_6h": 1.0,
    "rr_short_6h": 1.0,
    "levels": {
      "f5m": 75450.47,
      "f1h": 74922.47,
      "f4h": 73298.01,
      "c1h": 76278.36,
      "c4h": 78390.0,
      "c6h": 78390.0
    }
  },
  "eth": {
    "price": 2329.34,
    "ema200": 2320.2534565999335,
    "ema200_distance_pct": 0.3,
    "rsi": 42.53885978007603,
    "eagle": "NEUTRAL",
    "eagle_confidence": 30.0,
    "eagle_cvd": "NEUTRAL",
    "nano": "ACCUMULATION",
    "nano_position_pct": 42.1,
    "nano_zone_weight": "NEUTRAL",
    "nano_oi_context": "STALEMATE \u2014 Flat OI + Accumulation = Waiting for catalyst",
    "nano_direction_bias": "NEUTRAL",
    "vulture_bias": "LEAN LONG",
    "vulture_stack": "\ud83d\udcc9 BEARISH STACK (price < EMA9 < EMA21)",
    "trend": "\ud83d\udcc8 BULLISH \u2014 Confirmed uptrend (long-friendly, short-cautious)",
    "rr_best_long": 3.3,
    "rr_best_short": 0.3,
    "rr_best_timeframe": "4h",
    "rr_long_1h": 1.2,
    "rr_short_1h": 0.8,
    "rr_long_6h": 3.3,
    "rr_short_6h": 0.3,
    "levels": {
      "f5m": 2316.19,
      "f1h": 2299.25,
      "f4h": 2285.32,
      "c1h": 2361.2,
      "c4h": 2466.5,
      "c6h": 2466.5
    }
  },
  "symphony": {
    "state": "RANGE_BOUND",
    "confidence": 30
  },
  "macro": {
    "fg": 27,
    "weatherman": 0,
    "bias": "NEUTRAL"
  },
  "positions": [
    {
      "ticker": "KXBTCD-26APR2417-T71499.99",
      "asset": "BTC",
      "strike": 71500,
      "side": "no",
      "qty": 185,
      "entry": 0.14,
      "market_value": 25.9,
      "cost_basis": 25.9
    },
    {
      "ticker": "KXBTCD-26APR2417-T79999.99",
      "asset": "BTC",
      "strike": 80000,
      "side": "yes",
      "qty": 480,
      "entry": 0.13,
      "market_value": 62.4,
      "cost_basis": 62.4
    },
    {
      "ticker": "KXPGATOUR-RBH26-JSPI",
      "asset": "",
      "strike": 0,
      "side": "yes",
      "qty": 106,
      "entry": 0.034,
      "market_value": 3.6,
      "cost_basis": 3.6
    }
  ],
  "sell_orders": [
    {
      "ticker": "KXBTCD-26APR2417-T71499.99",
      "asset": "BTC",
      "strike": 71500,
      "side": "no",
      "price": 0.25,
      "qty": 184,
      "remaining": 185,
      "action": "sell"
    },
    {
      "ticker": "KXBTCD-26APR2417-T79999.99",
      "asset": "BTC",
      "strike": 80000,
      "side": "yes",
      "price": 0.25,
      "qty": 480,
      "remaining": 480,
      "action": "sell"
    }
  ],
  "buy_traps": [],
  "catalysts": [
    {
      "label": "JOLTS",
      "date": "2026-03-31T14:00:00Z",
      "risk": "HIGH"
    },
    {
      "label": "ADP",
      "date": "2026-04-01T12:15:00Z",
      "risk": "MED"
    },
    {
      "label": "ISM Mfg",
      "date": "2026-04-01T14:00:00Z",
      "risk": "MED"
    },
    {
      "label": "Tariff Day",
      "date": "2026-04-02T16:00:00Z",
      "risk": "MAX"
    },
    {
      "label": "NFP + Settle",
      "date": "2026-04-03T12:30:00Z",
      "risk": "MAX"
    }
  ],
  "price_history": {
    "BTC": {
      "series": [
        {
          "ts": "2026-04-18T15:49:22Z",
          "price": 76155.8,
          "eagle_phase": "NEUTRAL"
        },
        {
          "ts": "2026-04-18T16:49:52Z",
          "price": 75966.46,
          "eagle_phase": "CAPITULATION"
        },
        {
          "ts": "2026-04-18T17:50:14Z",
          "price": 75919.73,
          "eagle_phase": "CAPITULATION"
        },
        {
          "ts": "2026-04-18T18:50:38Z",
          "price": 75677.98,
          "eagle_phase": "CAPITULATION"
        },
        {
          "ts": "2026-04-18T19:51:18Z",
          "price": 75672.94,
          "eagle_phase": "CAPITULATION"
        },
        {
          "ts": "2026-04-18T20:51:48Z",
          "price": 75875.83,
          "eagle_phase": "ACCUMULATION"
        },
        {
          "ts": "2026-04-18T21:52:28Z",
          "price": 75801.87,
          "eagle_phase": "ACCUMULATION"
        },
        {
          "ts": "2026-04-18T22:52:51Z",
          "price": 75840.4,
          "eagle_phase": "ACCUMULATION"
        },
        {
          "ts": "2026-04-18T23:54:11Z",
          "price": 75747.56,
          "eagle_phase": "NEUTRAL"
        },
        {
          "ts": "2026-04-19T00:54:42Z",
          "price": 75682.0,
          "eagle_phase": "CAPITULATION"
        },
        {
          "ts": "2026-04-19T01:55:14Z",
          "price": 75653.99,
          "eagle_phase": "CAPITULATION"
        },
        {
          "ts": "2026-04-19T02:56:06Z",
          "price": 75595.92,
          "eagle_phase": "NEUTRAL"
        },
        {
          "ts": "2026-04-19T03:56:59Z",
          "price": 75612.01,
          "eagle_phase": "NEUTRAL"
        },
        {
          "ts": "2026-04-19T04:57:43Z",
          "price": 75702.88,
          "eagle_phase": "NEUTRAL"
        },
        {
          "ts": "2026-04-19T05:58:18Z",
          "price": 75586.67,
          "eagle_phase": "CAPITULATION"
        },
        {
          "ts": "2026-04-19T06:58:50Z",
          "price": 75425.81,
          "eagle_phase": "CAPITULATION"
        },
        {
          "ts": "2026-04-19T07:59:22Z",
          "price": 75294.54,
          "eagle_phase": "NEUTRAL"
        },
        {
          "ts": "2026-04-19T08:59:57Z",
          "price": 75265.46,
          "eagle_phase": "NEUTRAL"
        },
        {
          "ts": "2026-04-19T10:00:41Z",
          "price": 75009.32,
          "eagle_phase": "NEUTRAL"
        },
        {
          "ts": "2026-04-19T11:01:11Z",
          "price": 75271.87,
          "eagle_phase": "ACCUMULATION"
        },
        {
          "ts": "2026-04-19T12:01:39Z",
          "price": 75598.48,
          "eagle_phase": "NEUTRAL"
        },
        {
          "ts": "2026-04-19T13:02:38Z",
          "price": 75682.73,
          "eagle_phase": "NEUTRAL"
        },
        {
          "ts": "2026-04-19T14:09:54Z",
          "price": 75722.98,
          "eagle_phase": "NEUTRAL"
        },
        {
          "ts": "2026-04-19T15:10:28Z",
          "price": 76001.68,
          "eagle_phase": "NEUTRAL"
        }
      ],
      "high": 76155.8,
      "low": 75009.32
    },
    "ETH": {
      "series": [
        {
          "ts": "2026-04-18T15:49:22Z",
          "price": 2361.95,
          "eagle_phase": "ACCUMULATION"
        },
        {
          "ts": "2026-04-18T16:49:52Z",
          "price": 2363.29,
          "eagle_phase": "NEUTRAL"
        },
        {
          "ts": "2026-04-18T17:50:14Z",
          "price": 2364.9,
          "eagle_phase": "NEUTRAL"
        },
        {
          "ts": "2026-04-18T18:50:38Z",
          "price": 2350.16,
          "eagle_phase": "CAPITULATION"
        },
        {
          "ts": "2026-04-18T19:51:18Z",
          "price": 2350.85,
          "eagle_phase": "CAPITULATION"
        },
        {
          "ts": "2026-04-18T20:51:48Z",
          "price": 2355.8,
          "eagle_phase": "NEUTRAL"
        },
        {
          "ts": "2026-04-18T21:52:28Z",
          "price": 2353.42,
          "eagle_phase": "NEUTRAL"
        },
        {
          "ts": "2026-04-18T22:52:51Z",
          "price": 2358.7,
          "eagle_phase": "ACCUMULATION"
        },
        {
          "ts": "2026-04-18T23:54:11Z",
          "price": 2352.6,
          "eagle_phase": "NEUTRAL"
        },
        {
          "ts": "2026-04-19T00:54:42Z",
          "price": 2349.6,
          "eagle_phase": "CAPITULATION"
        },
        {
          "ts": "2026-04-19T01:55:14Z",
          "price": 2350.54,
          "eagle_phase": "CAPITULATION"
        },
        {
          "ts": "2026-04-19T02:56:06Z",
          "price": 2342.27,
          "eagle_phase": "CAPITULATION"
        },
        {
          "ts": "2026-04-19T03:56:59Z",
          "price": 2343.41,
          "eagle_phase": "NEUTRAL"
        },
        {
          "ts": "2026-04-19T04:57:43Z",
          "price": 2334.2,
          "eagle_phase": "CAPITULATION"
        },
        {
          "ts": "2026-04-19T05:58:18Z",
          "price": 2333.8,
          "eagle_phase": "CAPITULATION"
        },
        {
          "ts": "2026-04-19T06:58:50Z",
          "price": 2327.61,
          "eagle_phase": "ACCUMULATION"
        },
        {
          "ts": "2026-04-19T07:59:22Z",
          "price": 2317.32,
          "eagle_phase": "NEUTRAL"
        },
        {
          "ts": "2026-04-19T08:59:57Z",
          "price": 2318.9,
          "eagle_phase": "NEUTRAL"
        },
        {
          "ts": "2026-04-19T10:00:41Z",
          "price": 2309.2,
          "eagle_phase": "CAPITULATION"
        },
        {
          "ts": "2026-04-19T11:01:11Z",
          "price": 2320.02,
          "eagle_phase": "ACCUMULATION"
        },
        {
          "ts": "2026-04-19T12:01:39Z",
          "price": 2329.7,
          "eagle_phase": "NEUTRAL"
        },
        {
          "ts": "2026-04-19T13:02:38Z",
          "price": 2336.34,
          "eagle_phase": "NEUTRAL"
        },
        {
          "ts": "2026-04-19T14:09:54Z",
          "price": 2329.91,
          "eagle_phase": "ACCUMULATION"
        },
        {
          "ts": "2026-04-19T15:10:28Z",
          "price": 2336.95,
          "eagle_phase": "NEUTRAL"
        }
      ],
      "high": 2364.9,
      "low": 2309.2
    }
  },
  "fleet_summary": {
    "BTC": {
      "price": 75816.0,
      "eagle": "NEUTRAL",
      "nano": "DISTRIBUTION",
      "cvd": "STRONG BEARISH",
      "rsi": 51.20582050297455,
      "ema200_dist": 1.65,
      "rr_long": 1.0,
      "trend": "\ud83d\udcc8 BULLISH \u2014 Confirmed uptrend (long-friendly, short-cautious)",
      "funding": 0
    },
    "ETH": {
      "price": 2329.34,
      "eagle": "NEUTRAL",
      "nano": "ACCUMULATION",
      "cvd": "NEUTRAL",
      "rsi": 42.53885978007603,
      "ema200_dist": 0.3,
      "rr_long": 3.3,
      "trend": "\ud83d\udcc8 BULLISH \u2014 Confirmed uptrend (long-friendly, short-cautious)",
      "funding": -0.0009
    },
    "SOL": {
      "price": 86.4,
      "eagle": "NEUTRAL",
      "nano": "ACCUMULATION",
      "cvd": "MILD BULLISH",
      "rsi": 56.89348791867058,
      "ema200_dist": 0.83,
      "rr_long": 1.8,
      "trend": "\ud83d\udcc8 BULLISH \u2014 Confirmed uptrend (long-friendly, short-cautious)",
      "funding": -0.0005
    },
    "XRP": {
      "price": 1.4305,
      "eagle": "NEUTRAL",
      "nano": "DISTRIBUTION",
      "cvd": "STRONG BULLISH",
      "rsi": 51.20719765626324,
      "ema200_dist": 1.98,
      "rr_long": 2.0,
      "trend": "\ud83d\udcc8 BULLISH \u2014 Confirmed uptrend (long-friendly, short-cautious)",
      "funding": -9.999999999999999e-05
    },
    "DOGE": {
      "price": 0.09553,
      "eagle": "NEUTRAL",
      "nano": "DISTRIBUTION",
      "cvd": "MILD BULLISH",
      "rsi": 55.47371477802416,
      "ema200_dist": 0.4,
      "rr_long": 3.2,
      "trend": "\ud83d\udcc8 BULLISH \u2014 Confirmed uptrend (long-friendly, short-cautious)",
      "funding": 0.00030000000000000003
    },
    "BNB": {
      "price": 626.31,
      "eagle": "NEUTRAL",
      "nano": "DISTRIBUTION",
      "cvd": "NEUTRAL",
      "rsi": 47.161232209860415,
      "ema200_dist": 0.71,
      "rr_long": 2.1,
      "trend": "\ud83d\udcc8 BULLISH \u2014 Confirmed uptrend (long-friendly, short-cautious)",
      "funding": -0.0006000000000000001
    },
    "HYPE": {
      "price": 43.26,
      "eagle": "CAPITULATION",
      "nano": null,
      "cvd": "NEUTRAL",
      "rsi": 41.00209437223971,
      "ema200_dist": 0.07,
      "rr_long": 4.4,
      "trend": "\ud83d\udcc8 BULLISH \u2014 Confirmed uptrend (long-friendly, short-cautious)",
      "funding": null
    },
    "TAO": {
      "price": 246.12,
      "eagle": "NEUTRAL",
      "nano": null,
      "cvd": "STRONG BEARISH",
      "rsi": 50.59363136197967,
      "ema200_dist": -4.36,
      "rr_long": 6.3,
      "trend": "\ud83d\udcc8 BULLISH \u2014 Confirmed uptrend (long-friendly, short-cautious)",
      "funding": null
    },
    "ZEC": {
      "price": 324.57,
      "eagle": "ACCUMULATION",
      "nano": "ACCUMULATION",
      "cvd": "STRONG BEARISH",
      "rsi": 49.01944834507986,
      "ema200_dist": -4.6,
      "rr_long": 5.8,
      "trend": "\ud83d\udcc8 BULLISH \u2014 Confirmed uptrend (long-friendly, short-cautious)",
      "funding": -0.00019999999999999998
    },
    "LINK": {
      "price": 9.281,
      "eagle": "NEUTRAL",
      "nano": "DISTRIBUTION",
      "cvd": "STRONG BULLISH",
      "rsi": 48.91717313616527,
      "ema200_dist": 0.55,
      "rr_long": 3.5,
      "trend": "\ud83d\udcc8 BULLISH \u2014 Confirmed uptrend (long-friendly, short-cautious)",
      "funding": -0.00019999999999999998
    },
    "BCH": {
      "price": 443.04,
      "eagle": "NEUTRAL",
      "nano": "ACCUMULATION",
      "cvd": "STRONG BULLISH",
      "rsi": 48.329058436681464,
      "ema200_dist": 0.07,
      "rr_long": 2.1,
      "trend": "\ud83d\udcc8 BULLISH \u2014 Confirmed uptrend (long-friendly, short-cautious)",
      "funding": -0.00019999999999999998
    }
  },
  "top_edges": [
    {
      "asset": "SOL",
      "ticker": "KXSOLD-26APR2417-T89.9999",
      "strike": 89.9999,
      "days": 5.37,
      "edge_pct": 46.8,
      "signal": "BUY_YES",
      "direction": "OVER",
      "confidence": 94,
      "tier": "PROPHECY",
      "mkt_price": 5.0
    },
    {
      "asset": "XRP",
      "ticker": "KXXRPD-26APR2417-T1.5199",
      "strike": 1.5199,
      "days": 5.37,
      "edge_pct": 36.2,
      "signal": "BUY_YES",
      "direction": "OVER",
      "confidence": 95,
      "tier": "PROPHECY",
      "mkt_price": 12.0
    },
    {
      "asset": "XRP",
      "ticker": "KXXRPD-26APR2417-T1.4999",
      "strike": 1.4999,
      "days": 5.37,
      "edge_pct": 35.3,
      "signal": "BUY_YES",
      "direction": "OVER",
      "confidence": 95,
      "tier": "PROPHECY",
      "mkt_price": 18.0
    },
    {
      "asset": "XRP",
      "ticker": "KXXRPD-26APR2417-T1.5399",
      "strike": 1.5399,
      "days": 5.37,
      "edge_pct": 35.1,
      "signal": "BUY_YES",
      "direction": "OVER",
      "confidence": 95,
      "tier": "PROPHECY",
      "mkt_price": 8.0
    },
    {
      "asset": "XRP",
      "ticker": "KXXRPD-26APR2417-T1.5599",
      "strike": 1.5599,
      "days": 5.37,
      "edge_pct": 33.7,
      "signal": "BUY_YES",
      "direction": "OVER",
      "confidence": 95,
      "tier": "PROPHECY",
      "mkt_price": 5.0
    }
  ],
  "orderbook_depth": {
    "scanned_at": "2026-04-19T16:03:46.198710+00:00",
    "contracts": {
      "KXBTCD-26APR1913-T85799.99": {
        "ticker": "KXBTCD-26APR1913-T85799.99",
        "asset": "BTC",
        "mid_price": null,
        "spread_quality": "NO_DATA",
        "depth_quality": "DEEP",
        "imbalance": "NO_HEAVY",
        "whale_walls": [
          {
            "price": 0.04,
            "qty": 12768.0,
            "side": "no"
          },
          {
            "price": 0.05,
            "qty": 21871.0,
            "side": "no"
          },
          {
            "price": 0.11,
            "qty": 1277.0,
            "side": "no"
          },
          {
            "price": 0.12,
            "qty": 9112.0,
            "side": "no"
          },
          {
            "price": 0.35,
            "qty": 850.0,
            "side": "no"
          },
          {
            "price": 0.37,
            "qty": 764.0,
            "side": "no"
          }
        ],
        "mega_walls": [
          {
            "price": 0.04,
            "qty": 12768.0,
            "side": "no"
          },
          {
            "price": 0.05,
            "qty": 21871.0,
            "side": "no"
          },
          {
            "price": 0.11,
            "qty": 1277.0,
            "side": "no"
          },
          {
            "price": 0.12,
            "qty": 9112.0,
            "side": "no"
          }
        ],
        "has_whale_wall": true,
        "has_mega_wall": true
      },
      "KXBTCD-26APR1913-T85699.99": {
        "ticker": "KXBTCD-26APR1913-T85699.99",
        "asset": "BTC",
        "mid_price": null,
        "spread_quality": "NO_DATA",
        "depth_quality": "DEEP",
        "imbalance": "NO_HEAVY",
        "whale_walls": [
          {
            "price": 0.04,
            "qty": 12768.0,
            "side": "no"
          },
          {
            "price": 0.05,
            "qty": 21871.0,
            "side": "no"
          },
          {
            "price": 0.11,
            "qty": 1277.0,
            "side": "no"
          },
          {
            "price": 0.12,
            "qty": 9112.0,
            "side": "no"
          },
          {
            "price": 0.2,
            "qty": 785.0,
            "side": "no"
          },
          {
            "price": 0.22,
            "qty": 855.0,
            "side": "no"
          },
          {
            "price": 0.23,
            "qty": 800.0,
            "side": "no"
          },
          {
            "price": 0.24,
            "qty": 819.0,
            "side": "no"
          }
        ],
        "mega_walls": [
          {
            "price": 0.04,
            "qty": 12768.0,
            "side": "no"
          },
          {
            "price": 0.05,
            "qty": 21871.0,
            "side": "no"
          },
          {
            "price": 0.11,
            "qty": 1277.0,
            "side": "no"
          },
          {
            "price": 0.12,
            "qty": 9112.0,
            "side": "no"
          }
        ],
        "has_whale_wall": true,
        "has_mega_wall": true
      },
      "KXBTCD-26APR1913-T85599.99": {
        "ticker": "KXBTCD-26APR1913-T85599.99",
        "asset": "BTC",
        "mid_price": null,
        "spread_quality": "NO_DATA",
        "depth_quality": "DEEP",
        "imbalance": "NO_HEAVY",
        "whale_walls": [
          {
            "price": 0.04,
            "qty": 12768.0,
            "side": "no"
          },
          {
            "price": 0.05,
            "qty": 21871.0,
            "side": "no"
          },
          {
            "price": 0.11,
            "qty": 1277.0,
            "side": "no"
          },
          {
            "price": 0.12,
            "qty": 9112.0,
            "side": "no"
          },
          {
            "price": 0.2,
            "qty": 740.0,
            "side": "no"
          },
          {
            "price": 0.22,
            "qty": 772.0,
            "side": "no"
          },
          {
            "price": 0.23,
            "qty": 744.0,
            "side": "no"
          },
          {
            "price": 0.24,
            "qty": 751.0,
            "side": "no"
          },
          {
            "price": 0.25,
            "qty": 543.0,
            "side": "no"
          }
        ],
        "mega_walls": [
          {
            "price": 0.04,
            "qty": 12768.0,
            "side": "no"
          },
          {
            "price": 0.05,
            "qty": 21871.0,
            "side": "no"
          },
          {
            "price": 0.11,
            "qty": 1277.0,
            "side": "no"
          },
          {
            "price": 0.12,
            "qty": 9112.0,
            "side": "no"
          }
        ],
        "has_whale_wall": true,
        "has_mega_wall": true
      },
      "KXBTCD-26APR1913-T85499.99": {
        "ticker": "KXBTCD-26APR1913-T85499.99",
        "asset": "BTC",
        "mid_price": null,
        "spread_quality": "NO_DATA",
        "depth_quality": "DEEP",
        "imbalance": "NO_HEAVY",
        "whale_walls": [
          {
            "price": 0.04,
            "qty": 12768.0,
            "side": "no"
          },
          {
            "price": 0.05,
            "qty": 21871.0,
            "side": "no"
          },
          {
            "price": 0.11,
            "qty": 1277.0,
            "side": "no"
          },
          {
            "price": 0.12,
            "qty": 9112.0,
            "side": "no"
          },
          {
            "price": 0.35,
            "qty": 752.0,
            "side": "no"
          },
          {
            "price": 0.37,
            "qty": 863.0,
            "side": "no"
          }
        ],
        "mega_walls": [
          {
            "price": 0.04,
            "qty": 12768.0,
            "side": "no"
          },
          {
            "price": 0.05,
            "qty": 21871.0,
            "side": "no"
          },
          {
            "price": 0.11,
            "qty": 1277.0,
            "side": "no"
          },
          {
            "price": 0.12,
            "qty": 9112.0,
            "side": "no"
          }
        ],
        "has_whale_wall": true,
        "has_mega_wall": true
      },
      "KXBTCD-26APR1913-T85399.99": {
        "ticker": "KXBTCD-26APR1913-T85399.99",
        "asset": "BTC",
        "mid_price": null,
        "spread_quality": "NO_DATA",
        "depth_quality": "DEEP",
        "imbalance": "NO_HEAVY",
        "whale_walls": [
          {
            "price": 0.04,
            "qty": 12768.0,
            "side": "no"
          },
          {
            "price": 0.05,
            "qty": 21871.0,
            "side": "no"
          },
          {
            "price": 0.11,
            "qty": 1277.0,
            "side": "no"
          },
          {
            "price": 0.12,
            "qty": 9112.0,
            "side": "no"
          },
          {
            "price": 0.2,
            "qty": 802.0,
            "side": "no"
          },
          {
            "price": 0.22,
            "qty": 832.0,
            "side": "no"
          },
          {
            "price": 0.23,
            "qty": 836.0,
            "side": "no"
          },
          {
            "price": 0.24,
            "qty": 842.0,
            "side": "no"
          }
        ],
        "mega_walls": [
          {
            "price": 0.04,
            "qty": 12768.0,
            "side": "no"
          },
          {
            "price": 0.05,
            "qty": 21871.0,
            "side": "no"
          },
          {
            "price": 0.11,
            "qty": 1277.0,
            "side": "no"
          },
          {
            "price": 0.12,
            "qty": 9112.0,
            "side": "no"
          }
        ],
        "has_whale_wall": true,
        "has_mega_wall": true
      },
      "KXBTCD-26APR1913-T85299.99": {
        "ticker": "KXBTCD-26APR1913-T85299.99",
        "asset": "BTC",
        "mid_price": null,
        "spread_quality": "NO_DATA",
        "depth_quality": "DEEP",
        "imbalance": "NO_HEAVY",
        "whale_walls": [
          {
            "price": 0.04,
            "qty": 12768.0,
            "side": "no"
          },
          {
            "price": 0.05,
            "qty": 21871.0,
            "side": "no"
          },
          {
            "price": 0.11,
            "qty": 1277.0,
            "side": "no"
          },
          {
            "price": 0.12,
            "qty": 9112.0,
            "side": "no"
          },
          {
            "price": 0.35,
            "qty": 788.0,
            "side": "no"
          },
          {
            "price": 0.37,
            "qty": 845.0,
            "side": "no"
          }
        ],
        "mega_walls": [
          {
            "price": 0.04,
            "qty": 12768.0,
            "side": "no"
          },
          {
            "price": 0.05,
            "qty": 21871.0,
            "side": "no"
          },
          {
            "price": 0.11,
            "qty": 1277.0,
            "side": "no"
          },
          {
            "price": 0.12,
            "qty": 9112.0,
            "side": "no"
          }
        ],
        "has_whale_wall": true,
        "has_mega_wall": true
      },
      "KXBTCD-26APR1913-T85199.99": {
        "ticker": "KXBTCD-26APR1913-T85199.99",
        "asset": "BTC",
        "mid_price": null,
        "spread_quality": "NO_DATA",
        "depth_quality": "DEEP",
        "imbalance": "NO_HEAVY",
        "whale_walls": [
          {
            "price": 0.04,
            "qty": 12768.0,
            "side": "no"
          },
          {
            "price": 0.05,
            "qty": 21871.0,
            "side": "no"
          },
          {
            "price": 0.11,
            "qty": 1277.0,
            "side": "no"
          },
          {
            "price": 0.12,
            "qty": 9112.0,
            "side": "no"
          },
          {
            "price": 0.2,
            "qty": 760.0,
            "side": "no"
          },
          {
            "price": 0.22,
            "qty": 752.0,
            "side": "no"
          },
          {
            "price": 0.23,
            "qty": 748.0,
            "side": "no"
          },
          {
            "price": 0.24,
            "qty": 844.0,
            "side": "no"
          }
        ],
        "mega_walls": [
          {
            "price": 0.04,
            "qty": 12768.0,
            "side": "no"
          },
          {
            "price": 0.05,
            "qty": 21871.0,
            "side": "no"
          },
          {
            "price": 0.11,
            "qty": 1277.0,
            "side": "no"
          },
          {
            "price": 0.12,
            "qty": 9112.0,
            "side": "no"
          }
        ],
        "has_whale_wall": true,
        "has_mega_wall": true
      },
      "KXBTCD-26APR1913-T85099.99": {
        "ticker": "KXBTCD-26APR1913-T85099.99",
        "asset": "BTC",
        "mid_price": null,
        "spread_quality": "NO_DATA",
        "depth_quality": "DEEP",
        "imbalance": "NO_HEAVY",
        "whale_walls": [
          {
            "price": 0.04,
            "qty": 12768.0,
            "side": "no"
          },
          {
            "price": 0.05,
            "qty": 21871.0,
            "side": "no"
          },
          {
            "price": 0.11,
            "qty": 1277.0,
            "side": "no"
          },
          {
            "price": 0.12,
            "qty": 9112.0,
            "side": "no"
          },
          {
            "price": 0.35,
            "qty": 799.0,
            "side": "no"
          },
          {
            "price": 0.37,
            "qty": 790.0,
            "side": "no"
          },
          {
            "price": 0.38,
            "qty": 522.0,
            "side": "no"
          }
        ],
        "mega_walls": [
          {
            "price": 0.04,
            "qty": 12768.0,
            "side": "no"
          },
          {
            "price": 0.05,
            "qty": 21871.0,
            "side": "no"
          },
          {
            "price": 0.11,
            "qty": 1277.0,
            "side": "no"
          },
          {
            "price": 0.12,
            "qty": 9112.0,
            "side": "no"
          }
        ],
        "has_whale_wall": true,
        "has_mega_wall": true
      },
      "KXBTCD-26APR1913-T84999.99": {
        "ticker": "KXBTCD-26APR1913-T84999.99",
        "asset": "BTC",
        "mid_price": null,
        "spread_quality": "NO_DATA",
        "depth_quality": "DEEP",
        "imbalance": "NO_HEAVY",
        "whale_walls": [
          {
            "price": 0.04,
            "qty": 12768.0,
            "side": "no"
          },
          {
            "price": 0.11,
            "qty": 1277.0,
            "side": "no"
          }
        ],
        "mega_walls": [
          {
            "price": 0.04,
            "qty": 12768.0,
            "side": "no"
          },
          {
            "price": 0.11,
            "qty": 1277.0,
            "side": "no"
          }
        ],
        "has_whale_wall": true,
        "has_mega_wall": true
      },
      "KXBTCD-26APR1913-T84899.99": {
        "ticker": "KXBTCD-26APR1913-T84899.99",
        "asset": "BTC",
        "mid_price": null,
        "spread_quality": "NO_DATA",
        "depth_quality": "DEEP",
        "imbalance": "NO_HEAVY",
        "whale_walls": [
          {
            "price": 0.04,
            "qty": 12768.0,
            "side": "no"
          },
          {
            "price": 0.05,
            "qty": 21871.0,
            "side": "no"
          },
          {
            "price": 0.11,
            "qty": 1277.0,
            "side": "no"
          },
          {
            "price": 0.12,
            "qty": 9112.0,
            "side": "no"
          },
          {
            "price": 0.35,
            "qty": 800.0,
            "side": "no"
          },
          {
            "price": 0.37,
            "qty": 756.0,
            "side": "no"
          },
          {
            "price": 0.38,
            "qty": 555.0,
            "side": "no"
          }
        ],
        "mega_walls": [
          {
            "price": 0.04,
            "qty": 12768.0,
            "side": "no"
          },
          {
            "price": 0.05,
            "qty": 21871.0,
            "side": "no"
          },
          {
            "price": 0.11,
            "qty": 1277.0,
            "side": "no"
          },
          {
            "price": 0.12,
            "qty": 9112.0,
            "side": "no"
          }
        ],
        "has_whale_wall": true,
        "has_mega_wall": true
      },
      "KXBTCD-26APR1913-T84799.99": {
        "ticker": "KXBTCD-26APR1913-T84799.99",
        "asset": "BTC",
        "mid_price": null,
        "spread_quality": "NO_DATA",
        "depth_quality": "DEEP",
        "imbalance": "NO_HEAVY",
        "whale_walls": [
          {
            "price": 0.04,
            "qty": 12768.0,
            "side": "no"
          },
          {
            "price": 0.05,
            "qty": 21871.0,
            "side": "no"
          },
          {
            "price": 0.11,
            "qty": 1277.0,
            "side": "no"
          },
          {
            "price": 0.12,
            "qty": 9112.0,
            "side": "no"
          },
          {
            "price": 0.2,
            "qty": 787.0,
            "side": "no"
          },
          {
            "price": 0.22,
            "qty": 847.0,
            "side": "no"
          },
          {
            "price": 0.23,
            "qty": 849.0,
            "side": "no"
          },
          {
            "price": 0.24,
            "qty": 856.0,
            "side": "no"
          }
        ],
        "mega_walls": [
          {
            "price": 0.04,
            "qty": 12768.0,
            "side": "no"
          },
          {
            "price": 0.05,
            "qty": 21871.0,
            "side": "no"
          },
          {
            "price": 0.11,
            "qty": 1277.0,
            "side": "no"
          },
          {
            "price": 0.12,
            "qty": 9112.0,
            "side": "no"
          }
        ],
        "has_whale_wall": true,
        "has_mega_wall": true
      },
      "KXBTCD-26APR1913-T84699.99": {
        "ticker": "KXBTCD-26APR1913-T84699.99",
        "asset": "BTC",
        "mid_price": null,
        "spread_quality": "NO_DATA",
        "depth_quality": "DEEP",
        "imbalance": "NO_HEAVY",
        "whale_walls": [
          {
            "price": 0.04,
            "qty": 12715.0,
            "side": "no"
          },
          {
            "price": 0.05,
            "qty": 21871.0,
            "side": "no"
          },
          {
            "price": 0.11,
            "qty": 1272.0,
            "side": "no"
          },
          {
            "price": 0.12,
            "qty": 9112.0,
            "side": "no"
          },
          {
            "price": 0.35,
            "qty": 749.0,
            "side": "no"
          },
          {
            "price": 0.37,
            "qty": 833.0,
            "side": "no"
          },
          {
            "price": 0.38,
            "qty": 529.0,
            "side": "no"
          }
        ],
        "mega_walls": [
          {
            "price": 0.04,
            "qty": 12715.0,
            "side": "no"
          },
          {
            "price": 0.05,
            "qty": 21871.0,
            "side": "no"
          },
          {
            "price": 0.11,
            "qty": 1272.0,
            "side": "no"
          },
          {
            "price": 0.12,
            "qty": 9112.0,
            "side": "no"
          }
        ],
        "has_whale_wall": true,
        "has_mega_wall": true
      },
      "KXBTCD-26APR1913-T84599.99": {
        "ticker": "KXBTCD-26APR1913-T84599.99",
        "asset": "BTC",
        "mid_price": null,
        "spread_quality": "NO_DATA",
        "depth_quality": "DEEP",
        "imbalance": "NO_HEAVY",
        "whale_walls": [
          {
            "price": 0.04,
            "qty": 12660.0,
            "side": "no"
          },
          {
            "price": 0.11,
            "qty": 1267.0,
            "side": "no"
          }
        ],
        "mega_walls": [
          {
            "price": 0.04,
            "qty": 12660.0,
            "side": "no"
          },
          {
            "price": 0.11,
            "qty": 1267.0,
            "side": "no"
          }
        ],
        "has_whale_wall": true,
        "has_mega_wall": true
      },
      "KXBTCD-26APR1913-T84499.99": {
        "ticker": "KXBTCD-26APR1913-T84499.99",
        "asset": "BTC",
        "mid_price": null,
        "spread_quality": "NO_DATA",
        "depth_quality": "DEEP",
        "imbalance": "NO_HEAVY",
        "whale_walls": [
          {
            "price": 0.04,
            "qty": 12580.0,
            "side": "no"
          },
          {
            "price": 0.05,
            "qty": 21871.0,
            "side": "no"
          },
          {
            "price": 0.11,
            "qty": 1259.0,
            "side": "no"
          },
          {
            "price": 0.12,
            "qty": 9112.0,
            "side": "no"
          },
          {
            "price": 0.35,
            "qty": 784.0,
            "side": "no"
          },
          {
            "price": 0.37,
            "qty": 754.0,
            "side": "no"
          },
          {
            "price": 0.38,
            "qty": 573.0,
            "side": "no"
          }
        ],
        "mega_walls": [
          {
            "price": 0.04,
            "qty": 12580.0,
            "side": "no"
          },
          {
            "price": 0.05,
            "qty": 21871.0,
            "side": "no"
          },
          {
            "price": 0.11,
            "qty": 1259.0,
            "side": "no"
          },
          {
            "price": 0.12,
            "qty": 9112.0,
            "side": "no"
          }
        ],
        "has_whale_wall": true,
        "has_mega_wall": true
      },
      "KXBTCD-26APR1913-T84399.99": {
        "ticker": "KXBTCD-26APR1913-T84399.99",
        "asset": "BTC",
        "mid_price": null,
        "spread_quality": "NO_DATA",
        "depth_quality": "DEEP",
        "imbalance": "NO_HEAVY",
        "whale_walls": [
          {
            "price": 0.04,
            "qty": 12513.0,
            "side": "no"
          },
          {
            "price": 0.11,
            "qty": 1251.0,
            "side": "no"
          }
        ],
        "mega_walls": [
          {
            "price": 0.04,
            "qty": 12513.0,
            "side": "no"
          },
          {
            "price": 0.11,
            "qty": 1251.0,
            "side": "no"
          }
        ],
        "has_whale_wall": true,
        "has_mega_wall": true
      },
      "KXBTCD-26APR1913-T84299.99": {
        "ticker": "KXBTCD-26APR1913-T84299.99",
        "asset": "BTC",
        "mid_price": null,
        "spread_quality": "NO_DATA",
        "depth_quality": "DEEP",
        "imbalance": "NO_HEAVY",
        "whale_walls": [
          {
            "price": 0.04,
            "qty": 12452.0,
            "side": "no"
          },
          {
            "price": 0.11,
            "qty": 1245.0,
            "side": "no"
          }
        ],
        "mega_walls": [
          {
            "price": 0.04,
            "qty": 12452.0,
            "side": "no"
          },
          {
            "price": 0.11,
            "qty": 1245.0,
            "side": "no"
          }
        ],
        "has_whale_wall": true,
        "has_mega_wall": true
      },
      "KXBTCD-26APR1913-T84199.99": {
        "ticker": "KXBTCD-26APR1913-T84199.99",
        "asset": "BTC",
        "mid_price": null,
        "spread_quality": "NO_DATA",
        "depth_quality": "DEEP",
        "imbalance": "NO_HEAVY",
        "whale_walls": [
          {
            "price": 0.04,
            "qty": 12398.0,
            "side": "no"
          },
          {
            "price": 0.05,
            "qty": 21871.0,
            "side": "no"
          },
          {
            "price": 0.11,
            "qty": 1240.0,
            "side": "no"
          },
          {
            "price": 0.12,
            "qty": 9112.0,
            "side": "no"
          },
          {
            "price": 0.35,
            "qty": 749.0,
            "side": "no"
          },
          {
            "price": 0.37,
            "qty": 859.0,
            "side": "no"
          },
          {
            "price": 0.38,
            "qty": 503.0,
            "side": "no"
          }
        ],
        "mega_walls": [
          {
            "price": 0.04,
            "qty": 12398.0,
            "side": "no"
          },
          {
            "price": 0.05,
            "qty": 21871.0,
            "side": "no"
          },
          {
            "price": 0.11,
            "qty": 1240.0,
            "side": "no"
          },
          {
            "price": 0.12,
            "qty": 9112.0,
            "side": "no"
          }
        ],
        "has_whale_wall": true,
        "has_mega_wall": true
      },
      "KXBTCD-26APR1913-T84099.99": {
        "ticker": "KXBTCD-26APR1913-T84099.99",
        "asset": "BTC",
        "mid_price": null,
        "spread_quality": "NO_DATA",
        "depth_quality": "DEEP",
        "imbalance": "NO_HEAVY",
        "whale_walls": [
          {
            "price": 0.04,
            "qty": 12331.0,
            "side": "no"
          },
          {
            "price": 0.05,
            "qty": 21871.0,
            "side": "no"
          },
          {
            "price": 0.11,
            "qty": 1234.0,
            "side": "no"
          },
          {
            "price": 0.12,
            "qty": 9112.0,
            "side": "no"
          },
          {
            "price": 0.2,
            "qty": 736.0,
            "side": "no"
          },
          {
            "price": 0.22,
            "qty": 770.0,
            "side": "no"
          },
          {
            "price": 0.23,
            "qty": 824.0,
            "side": "no"
          },
          {
            "price": 0.24,
            "qty": 779.0,
            "side": "no"
          }
        ],
        "mega_walls": [
          {
            "price": 0.04,
            "qty": 12331.0,
            "side": "no"
          },
          {
            "price": 0.05,
            "qty": 21871.0,
            "side": "no"
          },
          {
            "price": 0.11,
            "qty": 1234.0,
            "side": "no"
          },
          {
            "price": 0.12,
            "qty": 9112.0,
            "side": "no"
          }
        ],
        "has_whale_wall": true,
        "has_mega_wall": true
      },
      "KXBTCD-26APR1913-T83999.99": {
        "ticker": "KXBTCD-26APR1913-T83999.99",
        "asset": "BTC",
        "mid_price": null,
        "spread_quality": "NO_DATA",
        "depth_quality": "DEEP",
        "imbalance": "NO_HEAVY",
        "whale_walls": [
          {
            "price": 0.04,
            "qty": 12263.0,
            "side": "no"
          },
          {
            "price": 0.05,
            "qty": 21871.0,
            "side": "no"
          },
          {
            "price": 0.11,
            "qty": 1226.0,
            "side": "no"
          },
          {
            "price": 0.12,
            "qty": 9112.0,
            "side": "no"
          },
          {
            "price": 0.35,
            "qty": 810.0,
            "side": "no"
          },
          {
            "price": 0.37,
            "qty": 804.0,
            "side": "no"
          }
        ],
        "mega_walls": [
          {
            "price": 0.04,
            "qty": 12263.0,
            "side": "no"
          },
          {
            "price": 0.05,
            "qty": 21871.0,
            "side": "no"
          },
          {
            "price": 0.11,
            "qty": 1226.0,
            "side": "no"
          },
          {
            "price": 0.12,
            "qty": 9112.0,
            "side": "no"
          }
        ],
        "has_whale_wall": true,
        "has_mega_wall": true
      },
      "KXBTCD-26APR1913-T83899.99": {
        "ticker": "KXBTCD-26APR1913-T83899.99",
        "asset": "BTC",
        "mid_price": null,
        "spread_quality": "NO_DATA",
        "depth_quality": "DEEP",
        "imbalance": "NO_HEAVY",
        "whale_walls": [
          {
            "price": 0.04,
            "qty": 12207.0,
            "side": "no"
          },
          {
            "price": 0.11,
            "qty": 1221.0,
            "side": "no"
          }
        ],
        "mega_walls": [
          {
            "price": 0.04,
            "qty": 12207.0,
            "side": "no"
          },
          {
            "price": 0.11,
            "qty": 1221.0,
            "side": "no"
          }
        ],
        "has_whale_wall": true,
        "has_mega_wall": true
      },
      "KXETHD-26APR1913-T3089.99": {
        "ticker": "KXETHD-26APR1913-T3089.99",
        "asset": "ETH",
        "mid_price": null,
        "spread_quality": "NO_DATA",
        "depth_quality": "DEEP",
        "imbalance": "NO_HEAVY",
        "whale_walls": [
          {
            "price": 0.04,
            "qty": 7661.0,
            "side": "no"
          },
          {
            "price": 0.05,
            "qty": 18794.0,
            "side": "no"
          },
          {
            "price": 0.11,
            "qty": 766.0,
            "side": "no"
          },
          {
            "price": 0.12,
            "qty": 7830.0,
            "side": "no"
          },
          {
            "price": 0.2,
            "qty": 783.0,
            "side": "no"
          },
          {
            "price": 0.22,
            "qty": 800.0,
            "side": "no"
          },
          {
            "price": 0.23,
            "qty": 804.0,
            "side": "no"
          },
          {
            "price": 0.24,
            "qty": 664.0,
            "side": "no"
          }
        ],
        "mega_walls": [
          {
            "price": 0.04,
            "qty": 7661.0,
            "side": "no"
          },
          {
            "price": 0.05,
            "qty": 18794.0,
            "side": "no"
          },
          {
            "price": 0.12,
            "qty": 7830.0,
            "side": "no"
          }
        ],
        "has_whale_wall": true,
        "has_mega_wall": true
      },
      "KXETHD-26APR1913-T3069.99": {
        "ticker": "KXETHD-26APR1913-T3069.99",
        "asset": "ETH",
        "mid_price": null,
        "spread_quality": "NO_DATA",
        "depth_quality": "DEEP",
        "imbalance": "NO_HEAVY",
        "whale_walls": [
          {
            "price": 0.04,
            "qty": 7661.0,
            "side": "no"
          },
          {
            "price": 0.05,
            "qty": 18794.0,
            "side": "no"
          },
          {
            "price": 0.11,
            "qty": 766.0,
            "side": "no"
          },
          {
            "price": 0.12,
            "qty": 7830.0,
            "side": "no"
          },
          {
            "price": 0.2,
            "qty": 821.0,
            "side": "no"
          },
          {
            "price": 0.22,
            "qty": 838.0,
            "side": "no"
          },
          {
            "price": 0.23,
            "qty": 791.0,
            "side": "no"
          },
          {
            "price": 0.24,
            "qty": 601.0,
            "side": "no"
          }
        ],
        "mega_walls": [
          {
            "price": 0.04,
            "qty": 7661.0,
            "side": "no"
          },
          {
            "price": 0.05,
            "qty": 18794.0,
            "side": "no"
          },
          {
            "price": 0.12,
            "qty": 7830.0,
            "side": "no"
          }
        ],
        "has_whale_wall": true,
        "has_mega_wall": true
      },
      "KXETHD-26APR1913-T3049.99": {
        "ticker": "KXETHD-26APR1913-T3049.99",
        "asset": "ETH",
        "mid_price": null,
        "spread_quality": "NO_DATA",
        "depth_quality": "DEEP",
        "imbalance": "NO_HEAVY",
        "whale_walls": [
          {
            "price": 0.04,
            "qty": 7661.0,
            "side": "no"
          },
          {
            "price": 0.05,
            "qty": 18794.0,
            "side": "no"
          },
          {
            "price": 0.11,
            "qty": 766.0,
            "side": "no"
          },
          {
            "price": 0.12,
            "qty": 7830.0,
            "side": "no"
          },
          {
            "price": 0.2,
            "qty": 787.0,
            "side": "no"
          },
          {
            "price": 0.22,
            "qty": 770.0,
            "side": "no"
          },
          {
            "price": 0.23,
            "qty": 747.0,
            "side": "no"
          },
          {
            "price": 0.24,
            "qty": 747.0,
            "side": "no"
          }
        ],
        "mega_walls": [
          {
            "price": 0.04,
            "qty": 7661.0,
            "side": "no"
          },
          {
            "price": 0.05,
            "qty": 18794.0,
            "side": "no"
          },
          {
            "price": 0.12,
            "qty": 7830.0,
            "side": "no"
          }
        ],
        "has_whale_wall": true,
        "has_mega_wall": true
      },
      "KXETHD-26APR1913-T3029.99": {
        "ticker": "KXETHD-26APR1913-T3029.99",
        "asset": "ETH",
        "mid_price": null,
        "spread_quality": "NO_DATA",
        "depth_quality": "DEEP",
        "imbalance": "NO_HEAVY",
        "whale_walls": [
          {
            "price": 0.04,
            "qty": 7661.0,
            "side": "no"
          },
          {
            "price": 0.05,
            "qty": 18794.0,
            "side": "no"
          },
          {
            "price": 0.11,
            "qty": 766.0,
            "side": "no"
          },
          {
            "price": 0.12,
            "qty": 7830.0,
            "side": "no"
          },
          {
            "price": 0.2,
            "qty": 810.0,
            "side": "no"
          },
          {
            "price": 0.22,
            "qty": 830.0,
            "side": "no"
          },
          {
            "price": 0.23,
            "qty": 828.0,
            "side": "no"
          },
          {
            "price": 0.24,
            "qty": 583.0,
            "side": "no"
          }
        ],
        "mega_walls": [
          {
            "price": 0.04,
            "qty": 7661.0,
            "side": "no"
          },
          {
            "price": 0.05,
            "qty": 18794.0,
            "side": "no"
          },
          {
            "price": 0.12,
            "qty": 7830.0,
            "side": "no"
          }
        ],
        "has_whale_wall": true,
        "has_mega_wall": true
      },
      "KXETHD-26APR1913-T3009.99": {
        "ticker": "KXETHD-26APR1913-T3009.99",
        "asset": "ETH",
        "mid_price": null,
        "spread_quality": "NO_DATA",
        "depth_quality": "DEEP",
        "imbalance": "NO_HEAVY",
        "whale_walls": [
          {
            "price": 0.04,
            "qty": 7661.0,
            "side": "no"
          },
          {
            "price": 0.05,
            "qty": 18794.0,
            "side": "no"
          },
          {
            "price": 0.11,
            "qty": 766.0,
            "side": "no"
          },
          {
            "price": 0.12,
            "qty": 7830.0,
            "side": "no"
          },
          {
            "price": 0.2,
            "qty": 856.0,
            "side": "no"
          },
          {
            "price": 0.22,
            "qty": 861.0,
            "side": "no"
          },
          {
            "price": 0.23,
            "qty": 780.0,
            "side": "no"
          },
          {
            "price": 0.24,
            "qty": 554.0,
            "side": "no"
          }
        ],
        "mega_walls": [
          {
            "price": 0.04,
            "qty": 7661.0,
            "side": "no"
          },
          {
            "price": 0.05,
            "qty": 18794.0,
            "side": "no"
          },
          {
            "price": 0.12,
            "qty": 7830.0,
            "side": "no"
          }
        ],
        "has_whale_wall": true,
        "has_mega_wall": true
      },
      "KXETHD-26APR1913-T2989.99": {
        "ticker": "KXETHD-26APR1913-T2989.99",
        "asset": "ETH",
        "mid_price": null,
        "spread_quality": "NO_DATA",
        "depth_quality": "DEEP",
        "imbalance": "NO_HEAVY",
        "whale_walls": [
          {
            "price": 0.04,
            "qty": 7661.0,
            "side": "no"
          },
          {
            "price": 0.05,
            "qty": 18794.0,
            "side": "no"
          },
          {
            "price": 0.11,
            "qty": 766.0,
            "side": "no"
          },
          {
            "price": 0.12,
            "qty": 7830.0,
            "side": "no"
          },
          {
            "price": 0.2,
            "qty": 853.0,
            "side": "no"
          },
          {
            "price": 0.22,
            "qty": 832.0,
            "side": "no"
          },
          {
            "price": 0.23,
            "qty": 861.0,
            "side": "no"
          },
          {
            "price": 0.24,
            "qty": 505.0,
            "side": "no"
          }
        ],
        "mega_walls": [
          {
            "price": 0.04,
            "qty": 7661.0,
            "side": "no"
          },
          {
            "price": 0.05,
            "qty": 18794.0,
            "side": "no"
          },
          {
            "price": 0.12,
            "qty": 7830.0,
            "side": "no"
          }
        ],
        "has_whale_wall": true,
        "has_mega_wall": true
      },
      "KXETHD-26APR1913-T2969.99": {
        "ticker": "KXETHD-26APR1913-T2969.99",
        "asset": "ETH",
        "mid_price": null,
        "spread_quality": "NO_DATA",
        "depth_quality": "DEEP",
        "imbalance": "NO_HEAVY",
        "whale_walls": [
          {
            "price": 0.04,
            "qty": 7661.0,
            "side": "no"
          },
          {
            "price": 0.05,
            "qty": 18794.0,
            "side": "no"
          },
          {
            "price": 0.11,
            "qty": 766.0,
            "side": "no"
          },
          {
            "price": 0.12,
            "qty": 7830.0,
            "side": "no"
          },
          {
            "price": 0.2,
            "qty": 815.0,
            "side": "no"
          },
          {
            "price": 0.22,
            "qty": 819.0,
            "side": "no"
          },
          {
            "price": 0.23,
            "qty": 772.0,
            "side": "no"
          },
          {
            "price": 0.24,
            "qty": 645.0,
            "side": "no"
          }
        ],
        "mega_walls": [
          {
            "price": 0.04,
            "qty": 7661.0,
            "side": "no"
          },
          {
            "price": 0.05,
            "qty": 18794.0,
            "side": "no"
          },
          {
            "price": 0.12,
            "qty": 7830.0,
            "side": "no"
          }
        ],
        "has_whale_wall": true,
        "has_mega_wall": true
      },
      "KXETHD-26APR1913-T2949.99": {
        "ticker": "KXETHD-26APR1913-T2949.99",
        "asset": "ETH",
        "mid_price": null,
        "spread_quality": "NO_DATA",
        "depth_quality": "DEEP",
        "imbalance": "NO_HEAVY",
        "whale_walls": [
          {
            "price": 0.04,
            "qty": 7661.0,
            "side": "no"
          },
          {
            "price": 0.05,
            "qty": 18794.0,
            "side": "no"
          },
          {
            "price": 0.11,
            "qty": 766.0,
            "side": "no"
          },
          {
            "price": 0.12,
            "qty": 7830.0,
            "side": "no"
          },
          {
            "price": 0.2,
            "qty": 742.0,
            "side": "no"
          },
          {
            "price": 0.22,
            "qty": 764.0,
            "side": "no"
          },
          {
            "price": 0.23,
            "qty": 843.0,
            "side": "no"
          },
          {
            "price": 0.24,
            "qty": 702.0,
            "side": "no"
          }
        ],
        "mega_walls": [
          {
            "price": 0.04,
            "qty": 7661.0,
            "side": "no"
          },
          {
            "price": 0.05,
            "qty": 18794.0,
            "side": "no"
          },
          {
            "price": 0.12,
            "qty": 7830.0,
            "side": "no"
          }
        ],
        "has_whale_wall": true,
        "has_mega_wall": true
      },
      "KXETHD-26APR1913-T2929.99": {
        "ticker": "KXETHD-26APR1913-T2929.99",
        "asset": "ETH",
        "mid_price": null,
        "spread_quality": "NO_DATA",
        "depth_quality": "DEEP",
        "imbalance": "NO_HEAVY",
        "whale_walls": [
          {
            "price": 0.04,
            "qty": 7661.0,
            "side": "no"
          },
          {
            "price": 0.05,
            "qty": 18794.0,
            "side": "no"
          },
          {
            "price": 0.11,
            "qty": 766.0,
            "side": "no"
          },
          {
            "price": 0.12,
            "qty": 7830.0,
            "side": "no"
          },
          {
            "price": 0.2,
            "qty": 804.0,
            "side": "no"
          },
          {
            "price": 0.22,
            "qty": 862.0,
            "side": "no"
          },
          {
            "price": 0.23,
            "qty": 783.0,
            "side": "no"
          },
          {
            "price": 0.24,
            "qty": 602.0,
            "side": "no"
          }
        ],
        "mega_walls": [
          {
            "price": 0.04,
            "qty": 7661.0,
            "side": "no"
          },
          {
            "price": 0.05,
            "qty": 18794.0,
            "side": "no"
          },
          {
            "price": 0.12,
            "qty": 7830.0,
            "side": "no"
          }
        ],
        "has_whale_wall": true,
        "has_mega_wall": true
      },
      "KXETHD-26APR1913-T2909.99": {
        "ticker": "KXETHD-26APR1913-T2909.99",
        "asset": "ETH",
        "mid_price": null,
        "spread_quality": "NO_DATA",
        "depth_quality": "DEEP",
        "imbalance": "NO_HEAVY",
        "whale_walls": [
          {
            "price": 0.04,
            "qty": 7661.0,
            "side": "no"
          },
          {
            "price": 0.05,
            "qty": 18794.0,
            "side": "no"
          },
          {
            "price": 0.11,
            "qty": 766.0,
            "side": "no"
          },
          {
            "price": 0.12,
            "qty": 7830.0,
            "side": "no"
          },
          {
            "price": 0.2,
            "qty": 760.0,
            "side": "no"
          },
          {
            "price": 0.22,
            "qty": 829.0,
            "side": "no"
          },
          {
            "price": 0.23,
            "qty": 851.0,
            "side": "no"
          },
          {
            "price": 0.24,
            "qty": 611.0,
            "side": "no"
          }
        ],
        "mega_walls": [
          {
            "price": 0.04,
            "qty": 7661.0,
            "side": "no"
          },
          {
            "price": 0.05,
            "qty": 18794.0,
            "side": "no"
          },
          {
            "price": 0.12,
            "qty": 7830.0,
            "side": "no"
          }
        ],
        "has_whale_wall": true,
        "has_mega_wall": true
      },
      "KXETHD-26APR1913-T2889.99": {
        "ticker": "KXETHD-26APR1913-T2889.99",
        "asset": "ETH",
        "mid_price": null,
        "spread_quality": "NO_DATA",
        "depth_quality": "DEEP",
        "imbalance": "NO_HEAVY",
        "whale_walls": [
          {
            "price": 0.04,
            "qty": 7661.0,
            "side": "no"
          },
          {
            "price": 0.05,
            "qty": 18794.0,
            "side": "no"
          },
          {
            "price": 0.11,
            "qty": 766.0,
            "side": "no"
          },
          {
            "price": 0.12,
            "qty": 7830.0,
            "side": "no"
          },
          {
            "price": 0.2,
            "qty": 791.0,
            "side": "no"
          },
          {
            "price": 0.22,
            "qty": 747.0,
            "side": "no"
          },
          {
            "price": 0.23,
            "qty": 821.0,
            "side": "no"
          },
          {
            "price": 0.24,
            "qty": 692.0,
            "side": "no"
          }
        ],
        "mega_walls": [
          {
            "price": 0.04,
            "qty": 7661.0,
            "side": "no"
          },
          {
            "price": 0.05,
            "qty": 18794.0,
            "side": "no"
          },
          {
            "price": 0.12,
            "qty": 7830.0,
            "side": "no"
          }
        ],
        "has_whale_wall": true,
        "has_mega_wall": true
      },
      "KXETHD-26APR1913-T2869.99": {
        "ticker": "KXETHD-26APR1913-T2869.99",
        "asset": "ETH",
        "mid_price": null,
        "spread_quality": "NO_DATA",
        "depth_quality": "DEEP",
        "imbalance": "NO_HEAVY",
        "whale_walls": [
          {
            "price": 0.04,
            "qty": 7661.0,
            "side": "no"
          },
          {
            "price": 0.05,
            "qty": 18794.0,
            "side": "no"
          },
          {
            "price": 0.11,
            "qty": 766.0,
            "side": "no"
          },
          {
            "price": 0.12,
            "qty": 7830.0,
            "side": "no"
          },
          {
            "price": 0.2,
            "qty": 804.0,
            "side": "no"
          },
          {
            "price": 0.22,
            "qty": 760.0,
            "side": "no"
          },
          {
            "price": 0.23,
            "qty": 860.0,
            "side": "no"
          },
          {
            "price": 0.24,
            "qty": 627.0,
            "side": "no"
          }
        ],
        "mega_walls": [
          {
            "price": 0.04,
            "qty": 7661.0,
            "side": "no"
          },
          {
            "price": 0.05,
            "qty": 18794.0,
            "side": "no"
          },
          {
            "price": 0.12,
            "qty": 7830.0,
            "side": "no"
          }
        ],
        "has_whale_wall": true,
        "has_mega_wall": true
      },
      "KXETHD-26APR1913-T2849.99": {
        "ticker": "KXETHD-26APR1913-T2849.99",
        "asset": "ETH",
        "mid_price": null,
        "spread_quality": "NO_DATA",
        "depth_quality": "DEEP",
        "imbalance": "NO_HEAVY",
        "whale_walls": [
          {
            "price": 0.04,
            "qty": 7663.0,
            "side": "no"
          },
          {
            "price": 0.05,
            "qty": 18794.0,
            "side": "no"
          },
          {
            "price": 0.11,
            "qty": 766.0,
            "side": "no"
          },
          {
            "price": 0.12,
            "qty": 7830.0,
            "side": "no"
          },
          {
            "price": 0.2,
            "qty": 836.0,
            "side": "no"
          },
          {
            "price": 0.22,
            "qty": 752.0,
            "side": "no"
          },
          {
            "price": 0.23,
            "qty": 851.0,
            "side": "no"
          },
          {
            "price": 0.24,
            "qty": 612.0,
            "side": "no"
          }
        ],
        "mega_walls": [
          {
            "price": 0.04,
            "qty": 7663.0,
            "side": "no"
          },
          {
            "price": 0.05,
            "qty": 18794.0,
            "side": "no"
          },
          {
            "price": 0.12,
            "qty": 7830.0,
            "side": "no"
          }
        ],
        "has_whale_wall": true,
        "has_mega_wall": true
      },
      "KXETHD-26APR1913-T2829.99": {
        "ticker": "KXETHD-26APR1913-T2829.99",
        "asset": "ETH",
        "mid_price": null,
        "spread_quality": "NO_DATA",
        "depth_quality": "DEEP",
        "imbalance": "NO_HEAVY",
        "whale_walls": [
          {
            "price": 0.04,
            "qty": 7663.0,
            "side": "no"
          },
          {
            "price": 0.05,
            "qty": 18794.0,
            "side": "no"
          },
          {
            "price": 0.11,
            "qty": 766.0,
            "side": "no"
          },
          {
            "price": 0.12,
            "qty": 7830.0,
            "side": "no"
          },
          {
            "price": 0.2,
            "qty": 738.0,
            "side": "no"
          },
          {
            "price": 0.22,
            "qty": 793.0,
            "side": "no"
          },
          {
            "price": 0.23,
            "qty": 797.0,
            "side": "no"
          },
          {
            "price": 0.24,
            "qty": 723.0,
            "side": "no"
          }
        ],
        "mega_walls": [
          {
            "price": 0.04,
            "qty": 7663.0,
            "side": "no"
          },
          {
            "price": 0.05,
            "qty": 18794.0,
            "side": "no"
          },
          {
            "price": 0.12,
            "qty": 7830.0,
            "side": "no"
          }
        ],
        "has_whale_wall": true,
        "has_mega_wall": true
      },
      "KXETHD-26APR1913-T2809.99": {
        "ticker": "KXETHD-26APR1913-T2809.99",
        "asset": "ETH",
        "mid_price": null,
        "spread_quality": "NO_DATA",
        "depth_quality": "DEEP",
        "imbalance": "NO_HEAVY",
        "whale_walls": [
          {
            "price": 0.04,
            "qty": 7663.0,
            "side": "no"
          },
          {
            "price": 0.05,
            "qty": 18794.0,
            "side": "no"
          },
          {
            "price": 0.11,
            "qty": 766.0,
            "side": "no"
          },
          {
            "price": 0.12,
            "qty": 7830.0,
            "side": "no"
          },
          {
            "price": 0.2,
            "qty": 844.0,
            "side": "no"
          },
          {
            "price": 0.22,
            "qty": 764.0,
            "side": "no"
          },
          {
            "price": 0.23,
            "qty": 792.0,
            "side": "no"
          },
          {
            "price": 0.24,
            "qty": 651.0,
            "side": "no"
          }
        ],
        "mega_walls": [
          {
            "price": 0.04,
            "qty": 7663.0,
            "side": "no"
          },
          {
            "price": 0.05,
            "qty": 18794.0,
            "side": "no"
          },
          {
            "price": 0.12,
            "qty": 7830.0,
            "side": "no"
          }
        ],
        "has_whale_wall": true,
        "has_mega_wall": true
      },
      "KXETHD-26APR1913-T2789.99": {
        "ticker": "KXETHD-26APR1913-T2789.99",
        "asset": "ETH",
        "mid_price": null,
        "spread_quality": "NO_DATA",
        "depth_quality": "DEEP",
        "imbalance": "NO_HEAVY",
        "whale_walls": [
          {
            "price": 0.04,
            "qty": 7663.0,
            "side": "no"
          },
          {
            "price": 0.05,
            "qty": 18794.0,
            "side": "no"
          },
          {
            "price": 0.11,
            "qty": 766.0,
            "side": "no"
          },
          {
            "price": 0.12,
            "qty": 7830.0,
            "side": "no"
          },
          {
            "price": 0.2,
            "qty": 776.0,
            "side": "no"
          },
          {
            "price": 0.22,
            "qty": 806.0,
            "side": "no"
          },
          {
            "price": 0.23,
            "qty": 759.0,
            "side": "no"
          },
          {
            "price": 0.24,
            "qty": 710.0,
            "side": "no"
          }
        ],
        "mega_walls": [
          {
            "price": 0.04,
            "qty": 7663.0,
            "side": "no"
          },
          {
            "price": 0.05,
            "qty": 18794.0,
            "side": "no"
          },
          {
            "price": 0.12,
            "qty": 7830.0,
            "side": "no"
          }
        ],
        "has_whale_wall": true,
        "has_mega_wall": true
      },
      "KXETHD-26APR1913-T2769.99": {
        "ticker": "KXETHD-26APR1913-T2769.99",
        "asset": "ETH",
        "mid_price": null,
        "spread_quality": "NO_DATA",
        "depth_quality": "DEEP",
        "imbalance": "NO_HEAVY",
        "whale_walls": [
          {
            "price": 0.04,
            "qty": 7626.0,
            "side": "no"
          },
          {
            "price": 0.05,
            "qty": 18794.0,
            "side": "no"
          },
          {
            "price": 0.11,
            "qty": 763.0,
            "side": "no"
          },
          {
            "price": 0.12,
            "qty": 7830.0,
            "side": "no"
          },
          {
            "price": 0.2,
            "qty": 764.0,
            "side": "no"
          },
          {
            "price": 0.22,
            "qty": 819.0,
            "side": "no"
          },
          {
            "price": 0.23,
            "qty": 823.0,
            "side": "no"
          },
          {
            "price": 0.24,
            "qty": 645.0,
            "side": "no"
          }
        ],
        "mega_walls": [
          {
            "price": 0.04,
            "qty": 7626.0,
            "side": "no"
          },
          {
            "price": 0.05,
            "qty": 18794.0,
            "side": "no"
          },
          {
            "price": 0.12,
            "qty": 7830.0,
            "side": "no"
          }
        ],
        "has_whale_wall": true,
        "has_mega_wall": true
      },
      "KXETHD-26APR1913-T2749.99": {
        "ticker": "KXETHD-26APR1913-T2749.99",
        "asset": "ETH",
        "mid_price": null,
        "spread_quality": "NO_DATA",
        "depth_quality": "DEEP",
        "imbalance": "NO_HEAVY",
        "whale_walls": [
          {
            "price": 0.04,
            "qty": 7444.0,
            "side": "no"
          },
          {
            "price": 0.05,
            "qty": 18794.0,
            "side": "no"
          },
          {
            "price": 0.11,
            "qty": 745.0,
            "side": "no"
          },
          {
            "price": 0.12,
            "qty": 7830.0,
            "side": "no"
          },
          {
            "price": 0.2,
            "qty": 844.0,
            "side": "no"
          },
          {
            "price": 0.22,
            "qty": 815.0,
            "side": "no"
          },
          {
            "price": 0.23,
            "qty": 792.0,
            "side": "no"
          },
          {
            "price": 0.24,
            "qty": 600.0,
            "side": "no"
          }
        ],
        "mega_walls": [
          {
            "price": 0.04,
            "qty": 7444.0,
            "side": "no"
          },
          {
            "price": 0.05,
            "qty": 18794.0,
            "side": "no"
          },
          {
            "price": 0.12,
            "qty": 7830.0,
            "side": "no"
          }
        ],
        "has_whale_wall": true,
        "has_mega_wall": true
      },
      "KXETHD-26APR1913-T2729.99": {
        "ticker": "KXETHD-26APR1913-T2729.99",
        "asset": "ETH",
        "mid_price": null,
        "spread_quality": "NO_DATA",
        "depth_quality": "DEEP",
        "imbalance": "NO_HEAVY",
        "whale_walls": [
          {
            "price": 0.04,
            "qty": 7250.0,
            "side": "no"
          },
          {
            "price": 0.05,
            "qty": 18794.0,
            "side": "no"
          },
          {
            "price": 0.11,
            "qty": 725.0,
            "side": "no"
          },
          {
            "price": 0.12,
            "qty": 7830.0,
            "side": "no"
          },
          {
            "price": 0.2,
            "qty": 855.0,
            "side": "no"
          },
          {
            "price": 0.22,
            "qty": 836.0,
            "side": "no"
          },
          {
            "price": 0.23,
            "qty": 834.0,
            "side": "no"
          },
          {
            "price": 0.24,
            "qty": 526.0,
            "side": "no"
          }
        ],
        "mega_walls": [
          {
            "price": 0.04,
            "qty": 7250.0,
            "side": "no"
          },
          {
            "price": 0.05,
            "qty": 18794.0,
            "side": "no"
          },
          {
            "price": 0.12,
            "qty": 7830.0,
            "side": "no"
          }
        ],
        "has_whale_wall": true,
        "has_mega_wall": true
      },
      "KXETHD-26APR1913-T2709.99": {
        "ticker": "KXETHD-26APR1913-T2709.99",
        "asset": "ETH",
        "mid_price": null,
        "spread_quality": "NO_DATA",
        "depth_quality": "DEEP",
        "imbalance": "NO_HEAVY",
        "whale_walls": [
          {
            "price": 0.04,
            "qty": 7042.0,
            "side": "no"
          },
          {
            "price": 0.05,
            "qty": 18794.0,
            "side": "no"
          },
          {
            "price": 0.11,
            "qty": 704.0,
            "side": "no"
          },
          {
            "price": 0.12,
            "qty": 7830.0,
            "side": "no"
          },
          {
            "price": 0.2,
            "qty": 760.0,
            "side": "no"
          },
          {
            "price": 0.22,
            "qty": 829.0,
            "side": "no"
          },
          {
            "price": 0.23,
            "qty": 825.0,
            "side": "no"
          },
          {
            "price": 0.24,
            "qty": 637.0,
            "side": "no"
          }
        ],
        "mega_walls": [
          {
            "price": 0.04,
            "qty": 7042.0,
            "side": "no"
          },
          {
            "price": 0.05,
            "qty": 18794.0,
            "side": "no"
          },
          {
            "price": 0.12,
            "qty": 7830.0,
            "side": "no"
          }
        ],
        "has_whale_wall": true,
        "has_mega_wall": true
      },
      "KXSOLD-26APR1913-T99.9999": {
        "ticker": "KXSOLD-26APR1913-T99.9999",
        "asset": "SOL",
        "mid_price": null,
        "spread_quality": "NO_DATA",
        "depth_quality": "DEEP",
        "imbalance": "NO_HEAVY",
        "whale_walls": [],
        "mega_walls": [],
        "has_whale_wall": false,
        "has_mega_wall": false
      },
      "KXSOLD-26APR1913-T98.9999": {
        "ticker": "KXSOLD-26APR1913-T98.9999",
        "asset": "SOL",
        "mid_price": null,
        "spread_quality": "NO_DATA",
        "depth_quality": "DEEP",
        "imbalance": "NO_HEAVY",
        "whale_walls": [],
        "mega_walls": [],
        "has_whale_wall": false,
        "has_mega_wall": false
      },
      "KXSOLD-26APR1913-T97.9999": {
        "ticker": "KXSOLD-26APR1913-T97.9999",
        "asset": "SOL",
        "mid_price": null,
        "spread_quality": "NO_DATA",
        "depth_quality": "DEEP",
        "imbalance": "NO_HEAVY",
        "whale_walls": [],
        "mega_walls": [],
        "has_whale_wall": false,
        "has_mega_wall": false
      },
      "KXSOLD-26APR1913-T96.9999": {
        "ticker": "KXSOLD-26APR1913-T96.9999",
        "asset": "SOL",
        "mid_price": null,
        "spread_quality": "NO_DATA",
        "depth_quality": "DEEP",
        "imbalance": "NO_HEAVY",
        "whale_walls": [],
        "mega_walls": [],
        "has_whale_wall": false,
        "has_mega_wall": false
      },
      "KXSOLD-26APR1913-T95.9999": {
        "ticker": "KXSOLD-26APR1913-T95.9999",
        "asset": "SOL",
        "mid_price": null,
        "spread_quality": "NO_DATA",
        "depth_quality": "DEEP",
        "imbalance": "NO_HEAVY",
        "whale_walls": [],
        "mega_walls": [],
        "has_whale_wall": false,
        "has_mega_wall": false
      },
      "KXSOLD-26APR1913-T94.9999": {
        "ticker": "KXSOLD-26APR1913-T94.9999",
        "asset": "SOL",
        "mid_price": null,
        "spread_quality": "NO_DATA",
        "depth_quality": "MODERATE",
        "imbalance": "NO_HEAVY",
        "whale_walls": [],
        "mega_walls": [],
        "has_whale_wall": false,
        "has_mega_wall": false
      },
      "KXSOLD-26APR1913-T93.9999": {
        "ticker": "KXSOLD-26APR1913-T93.9999",
        "asset": "SOL",
        "mid_price": null,
        "spread_quality": "NO_DATA",
        "depth_quality": "MODERATE",
        "imbalance": "NO_HEAVY",
        "whale_walls": [],
        "mega_walls": [],
        "has_whale_wall": false,
        "has_mega_wall": false
      },
      "KXSOLD-26APR1913-T92.9999": {
        "ticker": "KXSOLD-26APR1913-T92.9999",
        "asset": "SOL",
        "mid_price": null,
        "spread_quality": "NO_DATA",
        "depth_quality": "MODERATE",
        "imbalance": "NO_HEAVY",
        "whale_walls": [],
        "mega_walls": [],
        "has_whale_wall": false,
        "has_mega_wall": false
      },
      "KXSOLD-26APR1913-T91.9999": {
        "ticker": "KXSOLD-26APR1913-T91.9999",
        "asset": "SOL",
        "mid_price": null,
        "spread_quality": "NO_DATA",
        "depth_quality": "MODERATE",
        "imbalance": "NO_HEAVY",
        "whale_walls": [],
        "mega_walls": [],
        "has_whale_wall": false,
        "has_mega_wall": false
      },
      "KXSOLD-26APR1913-T90.9999": {
        "ticker": "KXSOLD-26APR1913-T90.9999",
        "asset": "SOL",
        "mid_price": null,
        "spread_quality": "NO_DATA",
        "depth_quality": "MODERATE",
        "imbalance": "NO_HEAVY",
        "whale_walls": [],
        "mega_walls": [],
        "has_whale_wall": false,
        "has_mega_wall": false
      },
      "KXSOLD-26APR1913-T89.9999": {
        "ticker": "KXSOLD-26APR1913-T89.9999",
        "asset": "SOL",
        "mid_price": null,
        "spread_quality": "NO_DATA",
        "depth_quality": "EMPTY",
        "imbalance": "NO_HEAVY",
        "whale_walls": [],
        "mega_walls": [],
        "has_whale_wall": false,
        "has_mega_wall": false
      },
      "KXSOLD-26APR1913-T88.9999": {
        "ticker": "KXSOLD-26APR1913-T88.9999",
        "asset": "SOL",
        "mid_price": null,
        "spread_quality": "NO_DATA",
        "depth_quality": "EMPTY",
        "imbalance": "NO_HEAVY",
        "whale_walls": [],
        "mega_walls": [],
        "has_whale_wall": false,
        "has_mega_wall": false
      },
      "KXSOLD-26APR1913-T87.9999": {
        "ticker": "KXSOLD-26APR1913-T87.9999",
        "asset": "SOL",
        "mid_price": null,
        "spread_quality": "NO_DATA",
        "depth_quality": "EMPTY",
        "imbalance": "NO_HEAVY",
        "whale_walls": [],
        "mega_walls": [],
        "has_whale_wall": false,
        "has_mega_wall": false
      },
      "KXSOLD-26APR1913-T86.9999": {
        "ticker": "KXSOLD-26APR1913-T86.9999",
        "asset": "SOL",
        "mid_price": 0.135,
        "spread_quality": "ILLIQUID",
        "depth_quality": "DEEP",
        "imbalance": "NO_HEAVY",
        "whale_walls": [],
        "mega_walls": [],
        "has_whale_wall": false,
        "has_mega_wall": false
      },
      "KXSOLD-26APR1913-T85.9999": {
        "ticker": "KXSOLD-26APR1913-T85.9999",
        "asset": "SOL",
        "mid_price": 0.68,
        "spread_quality": "ILLIQUID",
        "depth_quality": "DEEP",
        "imbalance": "YES_HEAVY",
        "whale_walls": [],
        "mega_walls": [],
        "has_whale_wall": false,
        "has_mega_wall": false
      },
      "KXSOLD-26APR1913-T84.9999": {
        "ticker": "KXSOLD-26APR1913-T84.9999",
        "asset": "SOL",
        "mid_price": 0.955,
        "spread_quality": "WIDE",
        "depth_quality": "MODERATE",
        "imbalance": "YES_HEAVY",
        "whale_walls": [],
        "mega_walls": [],
        "has_whale_wall": false,
        "has_mega_wall": false
      },
      "KXSOLD-26APR1913-T83.9999": {
        "ticker": "KXSOLD-26APR1913-T83.9999",
        "asset": "SOL",
        "mid_price": null,
        "spread_quality": "NO_DATA",
        "depth_quality": "EMPTY",
        "imbalance": "NO_HEAVY",
        "whale_walls": [],
        "mega_walls": [],
        "has_whale_wall": false,
        "has_mega_wall": false
      },
      "KXSOLD-26APR1913-T82.9999": {
        "ticker": "KXSOLD-26APR1913-T82.9999",
        "asset": "SOL",
        "mid_price": null,
        "spread_quality": "NO_DATA",
        "depth_quality": "EMPTY",
        "imbalance": "NO_HEAVY",
        "whale_walls": [],
        "mega_walls": [],
        "has_whale_wall": false,
        "has_mega_wall": false
      },
      "KXSOLD-26APR1913-T81.9999": {
        "ticker": "KXSOLD-26APR1913-T81.9999",
        "asset": "SOL",
        "mid_price": 0.985,
        "spread_quality": "TIGHT",
        "depth_quality": "MODERATE",
        "imbalance": "YES_HEAVY",
        "whale_walls": [],
        "mega_walls": [],
        "has_whale_wall": false,
        "has_mega_wall": false
      },
      "KXSOLD-26APR1913-T80.9999": {
        "ticker": "KXSOLD-26APR1913-T80.9999",
        "asset": "SOL",
        "mid_price": null,
        "spread_quality": "NO_DATA",
        "depth_quality": "MODERATE",
        "imbalance": "YES_HEAVY",
        "whale_walls": [],
        "mega_walls": [],
        "has_whale_wall": false,
        "has_mega_wall": false
      }
    }
  },
  "ledger": {
    "total_trades": 22,
    "wins": 19,
    "losses": 3,
    "win_rate": 86.4,
    "realized_pnl": 1151.99,
    "week_pnl": 499.21
  }
}